cpggen/__init__.py
cpggen/atom/__init__.py
cpggen/atom/atom.zip
cpggen/atom/atom.zip.sha512
cpggen/cli.py
cpggen/executor.py
cpggen/logger.py
cpggen/source/__init__.py
cpggen/source/ghsa.py
cpggen/utils.py
cpggen-1.9.0.dist-info/LICENSE
cpggen-1.9.0.dist-info/METADATA
cpggen-1.9.0.dist-info/WHEEL
cpggen-1.9.0.dist-info/entry_points.txt
cpggen-1.9.0.dist-info/RECORD
