Metadata-Version: 2.1
Name: cpggen
Version: 1.9.0
Summary: Generate CPG for multiple languages for code and threat analysis
Home-page: https://github.com/AppThreat/cpggen
License: Apache-2.0
Keywords: joern,code analysis,static analysis,cpg,code property graph,atom,threat analysis
Author: Team AppThreat
Author-email: cloud@appthreat.com
Requires-Python: >=3.8.1,<3.12
Classifier: Development Status :: 5 - Production/Stable
Classifier: Intended Audience :: Developers
Classifier: Intended Audience :: System Administrators
Classifier: License :: OSI Approved :: Apache Software License
Classifier: Operating System :: OS Independent
Classifier: Programming Language :: Python :: 3
Classifier: Programming Language :: Python :: 3.9
Classifier: Programming Language :: Python :: 3.10
Classifier: Programming Language :: Python :: 3.11
Classifier: Programming Language :: Python :: 3.8
Classifier: Topic :: Security
Classifier: Topic :: Utilities
Requires-Dist: gitpython (>=3.1.31,<4.0.0)
Requires-Dist: httpx (>=0.24.1,<0.25.0)
Requires-Dist: packageurl-python (>=0.11.1,<0.12.0)
Requires-Dist: psutil (>=5.9.5,<6.0.0)
Requires-Dist: quart (>=0.18.4,<0.19.0)
Requires-Dist: rich (>=13.4.2,<14.0.0)
Project-URL: Repository, https://github.com/AppThreat/cpggen
